{
  "package.json": "{\n  \"name\": \"counter-app\",\n  \"private\": true,\n  \"version\": \"0.0.0\",\n  \"type\": \"module\",\n  \"scripts\": {\n    \"dev\": \"vite\",\n    \"build\": \"vite build\",\n    \"preview\": \"vite preview\",\n    \"test\": \"vitest\"\n  },\n  \"dependencies\": {\n    \"react\": \"^18.2.0\",\n    \"react-dom\": \"^18.2.0\"\n  },\n  \"devDependencies\": {\n    \"@testing-library/jest-dom\": \"^6.1.5\",\n    \"@testing-library/react\": \"^14.1.2\",\n    \"@types/react\": \"^18.2.43\",\n    \"@types/react-dom\": \"^18.2.17\",\n    \"@vitejs/plugin-react\": \"^4.2.1\",\n    \"autoprefixer\": \"^10.4.16\",\n    \"jsdom\": \"^23.0.1\",\n    \"postcss\": \"^8.4.32\",\n    \"tailwindcss\": \"^3.4.0\",\n    \"vite\": \"^5.0.8\",\n    \"vitest\": \"^1.1.0\"\n  }\n}",
  "vite.config.js": "import { defineConfig } from 'vite';\nimport react from '@vitejs/plugin-react';\n\nexport default defineConfig({\n  plugins: [react()],\n  test: {\n    globals: true,\n    environment: 'jsdom',\n    setupFiles: './src/__tests__/setup.js',\n  },\n  esbuild: {\n    loader: 'jsx',\n    include: /src\\/.*\\.jsx?$/,\n    exclude: [],\n  },\n  optimizeDeps: {\n    esbuildOptions: {\n      loader: {\n        '.js': 'jsx',\n      },\n    },\n  },\n});",
  "tailwind.config.js": "/** @type {import('tailwindcss').Config} */\nexport default {\n  content: [\n    \"./index.html\",\n    \"./src/**/*.{js,ts,jsx,tsx}\",\n  ],\n  theme: {\n    extend: {},\n  },\n  plugins: [],\n};",
  "postcss.config.js": "export default {\n  plugins: {\n    tailwindcss: {},\n    autoprefixer: {},\n  },\n};",
  "index.html": "<!doctype html>\n<html lang=\"en\">\n  <head>\n    <meta charset=\"UTF-8\" />\n    <link rel=\"icon\" type=\"image/svg+xml\" href=\"/vite.svg\" />\n    <meta name=\"viewport\" content=\"width=device-width, initial-scale=1.0\" />\n    <title>Counter App</title>\n  </head>\n  <body>\n    <div id=\"root\"></div>\n    <script type=\"module\" src=\"/src/main.jsx\"></script>\n  </body>\n</html>",
  "src/main.jsx": "import React from 'react';\nimport ReactDOM from 'react-dom/client';\nimport App from './App.jsx';\nimport './index.css';\n\nReactDOM.createRoot(document.getElementById('root')).render(\n  <React.StrictMode>\n    <App />\n  </React.StrictMode>,\n);",
  "src/App.jsx": "import Counter from './components/Counter';\n\nfunction App() {\n  return (\n    <div className=\"min-h-screen bg-gradient-to-br from-blue-50 to-indigo-100 flex items-center justify-center p-4\">\n      <div className=\"bg-white rounded-2xl shadow-2xl p-8 max-w-md w-full\">\n        <h1 className=\"text-4xl font-bold text-center mb-8 text-indigo-600\">\n          Counter App\n        </h1>\n        <Counter />\n      </div>\n    </div>\n  );\n}\n\nexport default App;",
  "src/index.css": "@tailwind base;\n@tailwind components;\n@tailwind utilities;",
  "src/components/Counter.jsx": "import { useState, useEffect } from 'react';\n\nfunction Counter() {\n  const [count, setCount] = useState(() => {\n    const savedCount = localStorage.getItem('counterValue');\n    return savedCount !== null ? parseInt(savedCount, 10) : 0;\n  });\n\n  useEffect(() => {\n    localStorage.setItem('counterValue', count.toString());\n  }, [count]);\n\n  const increment = () => setCount(count + 1);\n  const decrement = () => setCount(count - 1);\n  const reset = () => setCount(0);\n\n  return (\n    <div className=\"flex flex-col items-center space-y-6\">\n      <div className=\"text-6xl font-bold text-indigo-600 mb-4\" data-testid=\"counter-display\">\n        {count}\n      </div>\n      <div className=\"flex gap-4 flex-wrap justify-center\">\n        <button\n          onClick={decrement}\n          className=\"px-6 py-3 bg-red-500 hover:bg-red-600 text-white font-semibold rounded-lg shadow-md transition-colors duration-200 focus:outline-none focus:ring-2 focus:ring-red-400 focus:ring-offset-2\"\n          data-testid=\"decrement-button\"\n        >\n          Decrement\n        </button>\n        <button\n          onClick={reset}\n          className=\"px-6 py-3 bg-gray-500 hover:bg-gray-600 text-white font-semibold rounded-lg shadow-md transition-colors duration-200 focus:outline-none focus:ring-2 focus:ring-gray-400 focus:ring-offset-2\"\n          data-testid=\"reset-button\"\n        >\n          Reset\n        </button>\n        <button\n          onClick={increment}\n          className=\"px-6 py-3 bg-green-500 hover:bg-green-600 text-white font-semibold rounded-lg shadow-md transition-colors duration-200 focus:outline-none focus:ring-2 focus:ring-green-400 focus:ring-offset-2\"\n          data-testid=\"increment-button\"\n        >\n          Increment\n        </button>\n      </div>\n    </div>\n  );\n}\n\nexport default Counter;",
  "src/__tests__/setup.js": "import '@testing-library/jest-dom';",
  "src/__tests__/counter.test.js": "import { describe, it, expect, beforeEach, vi } from 'vitest';\nimport { render, screen, fireEvent } from '@testing-library/react';\nimport Counter from '../components/Counter';\n\ndescribe('Counter Component', () => {\n  beforeEach(() => {\n    localStorage.clear();\n  });\n\n  it('renders the counter component', () => {\n    render(<Counter />);\n    const counterDisplay = screen.getByTestId('counter-display');\n    expect(counterDisplay).toBeInTheDocument();\n  });\n\n  it('initializes counter at 0', () => {\n    render(<Counter />);\n    const counterDisplay = screen.getByTestId('counter-display');\n    expect(counterDisplay).toHaveTextContent('0');\n  });\n\n  it('increments the counter when increment button is clicked', () => {\n    render(<Counter />);\n    const incrementButton = screen.getByTestId('increment-button');\n    const counterDisplay = screen.getByTestId('counter-display');\n    \n    fireEvent.click(incrementButton);\n    expect(counterDisplay).toHaveTextContent('1');\n    \n    fireEvent.click(incrementButton);\n    expect(counterDisplay).toHaveTextContent('2');\n  });\n\n  it('decrements the counter when decrement button is clicked', () => {\n    render(<Counter />);\n    const decrementButton = screen.getByTestId('decrement-button');\n    const counterDisplay = screen.getByTestId('counter-display');\n    \n    fireEvent.click(decrementButton);\n    expect(counterDisplay).toHaveTextContent('-1');\n    \n    fireEvent.click(decrementButton);\n    expect(counterDisplay).toHaveTextContent('-2');\n  });\n\n  it('resets the counter to zero when reset button is clicked', () => {\n    render(<Counter />);\n    const incrementButton = screen.getByTestId('increment-button');\n    const resetButton = screen.getByTestId('reset-button');\n    const counterDisplay = screen.getByTestId('counter-display');\n    \n    fireEvent.click(incrementButton);\n    fireEvent.click(incrementButton);\n    fireEvent.click(incrementButton);\n    expect(counterDisplay).toHaveTextContent('3');\n    \n    fireEvent.click(resetButton);\n    expect(counterDisplay).toHaveTextContent('0');\n  });\n\n  it('persists counter value in localStorage', () => {\n    render(<Counter />);\n    const incrementButton = screen.getByTestId('increment-button');\n    \n    fireEvent.click(incrementButton);\n    fireEvent.click(incrementButton);\n    fireEvent.click(incrementButton);\n    \n    expect(localStorage.getItem('counterValue')).toBe('3');\n  });\n\n  it('loads counter value from localStorage on mount', () => {\n    localStorage.setItem('counterValue', '42');\n    \n    render(<Counter />);\n    const counterDisplay = screen.getByTestId('counter-display');\n    \n    expect(counterDisplay).toHaveTextContent('42');\n  });\n\n  it('updates localStorage when counter changes', () => {\n    render(<Counter />);\n    const incrementButton = screen.getByTestId('increment-button');\n    const decrementButton = screen.getByTestId('decrement-button');\n    const resetButton = screen.getByTestId('reset-button');\n    \n    fireEvent.click(incrementButton);\n    expect(localStorage.getItem('counterValue')).toBe('1');\n    \n    fireEvent.click(decrementButton);\n    expect(localStorage.getItem('counterValue')).toBe('0');\n    \n    fireEvent.click(incrementButton);\n    fireEvent.click(incrementButton);\n    expect(localStorage.getItem('counterValue')).toBe('2');\n    \n    fireEvent.click(resetButton);\n    expect(localStorage.getItem('counterValue')).toBe('0');\n  });\n});",
  ".gitignore": "# Logs\nlogs\n*.log\nnpm-debug.log*\nyarn-debug.log*\nyarn-error.log*\npnpm-debug.log*\nlerna-debug.log*\n\nnode_modules\ndist\ndist-ssr\n*.local\n\n# Editor directories and files\n.vscode/*\n!.vscode/extensions.json\n.idea\n.DS_Store\n*.suo\n*.ntvs*\n*.njsproj\n*.sln\n*.sw?",
  "README.md": "# Counter App\n\nA simple counter application built with React, Vite, Tailwind CSS, and Vitest.\n\n## Features\n\n- Increment, decrement, and reset counter\n- Styled with Tailwind CSS\n- Persists counter value in localStorage\n- Comprehensive test coverage with Vitest\n\n## Getting Started\n\n### Installation\n\n```bash\nnpm install\n```\n\n### Development\n\n```bash\nnpm run dev\n```\n\n### Build\n\n```bash\nnpm run build\n```\n\n### Test\n\n```bash\nnpm test\n```\n\n## Project Structure\n\n```\n.\n├── index.html\n├── package.json\n├── postcss.config.js\n├── tailwind.config.js\n├── vite.config.js\n└── src\n    ├── App.jsx\n    ├── index.css\n    ├── main.jsx\n    ├── __tests__\n    │   ├── counter.test.js\n    │   └── setup.js\n    └── components\n        └── Counter.jsx\n```\n\n## Testing\n\nThe app includes comprehensive tests that verify:\n- Counter renders correctly\n- Buttons update the count\n- Reset sets count to zero\n- localStorage persists the value"
}
